README.md
setup.cfg
setup.py
operon_sling.egg-info/PKG-INFO
operon_sling.egg-info/SOURCES.txt
operon_sling.egg-info/dependency_links.txt
operon_sling.egg-info/requires.txt
operon_sling.egg-info/top_level.txt
scripts/sling
sling/__init__.py
sling/create_db.py
sling/filter.py
sling/group.py
sling/prepare.py
sling/scan.py
sling/utils.py
sling/data/DATABASES
sling/data/RND_pump
sling/data/RND_pump.h3f
sling/data/RND_pump.h3i
sling/data/RND_pump.h3m
sling/data/RND_pump.h3p
sling/data/RND_pump.txt
sling/data/default.txt
sling/data/domains.txt
sling/data/domains_to_ignore.txt
sling/data/toxins
sling/data/toxins.h3f
sling/data/toxins.h3i
sling/data/toxins.h3m
sling/data/toxins.h3p
sling/data/toxins.txt
sling/tasks/__init__.py
sling/tasks/create_db.py
sling/tasks/filter.py
sling/tasks/group.py
sling/tasks/prepare.py
sling/tasks/run.py
sling/tasks/scan.py
sling/tasks/version.py
sling/tasks/view_dbs.py