Metadata-Version: 1.0
Name: operon-sling
Version: 2.0.0
Summary: sling: a tool to search for linked gene arrays in bacterial datasets
Home-page: https://github.com/ghoresh11/sling/wiki
Author: Gal Horesh
Author-email: gh11@sanger.ac.uk
License: UNKNOWN
Platform: UNKNOWN
